cl4py/__init__.py
cl4py/circularity.py
cl4py/data.py
cl4py/lisp.py
cl4py/py.lisp
cl4py/reader.py
cl4py/writer.py
cl4py-1.8.2.dist-info/LICENSE
cl4py-1.8.2.dist-info/METADATA
cl4py-1.8.2.dist-info/WHEEL
cl4py-1.8.2.dist-info/top_level.txt
cl4py-1.8.2.dist-info/RECORD
