Metadata-Version: 2.1
Name: cl4py
Version: 1.8.2
Summary: Common Lisp for Python
Home-page: https://github.com/marcoheisig/cl4py
Author: Marco Heisig
Author-email: marco.heisig@fau.de
License: MIT
Keywords: foreign functions FFI
Classifier: Development Status :: 5 - Production/Stable
Classifier: Intended Audience :: Developers
Classifier: License :: OSI Approved :: MIT License
Classifier: Programming Language :: Python :: 3
Classifier: Programming Language :: Python :: 3.4
Classifier: Programming Language :: Python :: 3.5
Classifier: Programming Language :: Python :: 3.6
Classifier: Programming Language :: Python :: 3.7
Classifier: Programming Language :: Lisp
License-File: LICENSE
Requires-Dist: numpy
